XComsians/NLP.py
XComsians/__init__.py
XComsians-0.0.3.dist-info/LICENSE
XComsians-0.0.3.dist-info/METADATA
XComsians-0.0.3.dist-info/WHEEL
XComsians-0.0.3.dist-info/top_level.txt
XComsians-0.0.3.dist-info/RECORD
