Metadata-Version: 2.1
Name: XComsians
Version: 0.0.3
Summary: NLP Preprocessing By XComsians
Author: Engr. Bilal Ahmad
Author-email: bilalahmad176176@gmail.com
Keywords: python,XComsians,NLP Preprocessing,preprocessing by XComsians,Engr. Bilal Ahmad
Classifier: Development Status :: 1 - Planning
Classifier: Intended Audience :: Developers
Classifier: Programming Language :: Python :: 3
Classifier: Operating System :: Unix
Classifier: Operating System :: MacOS :: MacOS X
Classifier: Operating System :: Microsoft :: Windows
License-File: LICENSE
